madnbdev/__init__.py
madnbdev/_modidx.py
madnbdev/agent.py
madnbdev/basic.py
madnbdev/intro.py
madnbdev-0.0.2.dist-info/LICENSE
madnbdev-0.0.2.dist-info/METADATA
madnbdev-0.0.2.dist-info/WHEEL
madnbdev-0.0.2.dist-info/entry_points.txt
madnbdev-0.0.2.dist-info/top_level.txt
madnbdev-0.0.2.dist-info/RECORD
