Metadata-Version: 2.1
Name: madnbdev
Version: 0.0.2
Summary: A library that will change the world
Home-page: https://github.com/ProblemSolversGuild/madnbdev
Author: Kevin Bird
Author-email: kevinbird15@gmail.com
License: Apache Software License 2.0
Keywords: nbdev jupyter notebook python
Platform: UNKNOWN
Classifier: Development Status :: 4 - Beta
Classifier: Intended Audience :: Developers
Classifier: Natural Language :: English
Classifier: Programming Language :: Python :: 3.7
Classifier: Programming Language :: Python :: 3.8
Classifier: Programming Language :: Python :: 3.9
Classifier: Programming Language :: Python :: 3.10
Classifier: License :: OSI Approved :: Apache Software License
Requires-Python: >=3.7
License-File: LICENSE
Requires-Dist: fastcore
Requires-Dist: openai
Provides-Extra: dev
Requires-Dist: twine ; extra == 'dev'
